vanidl/__init__.py
vanidl/analyzer.py
vanidl/configuraton.py
vanidl/constants.py
vanidl/error_code.py
vanidl-0.0.8.dist-info/LICENSE
vanidl-0.0.8.dist-info/METADATA
vanidl-0.0.8.dist-info/WHEEL
vanidl-0.0.8.dist-info/top_level.txt
vanidl-0.0.8.dist-info/RECORD
