Metadata-Version: 2.1
Name: vanidl
Version: 0.0.8
Summary: VaniDL is an tool for analyzing I/O patterns and behavior with Deep Learning Applications.
Home-page: https://github.com/hariharan-devarajan/vanidl
Author: Hariharan Devarajan
Author-email: mani.hariharan@gmail.com
License: UNKNOWN
Project-URL: Bug Tracker, https://github.com/hariharan-devarajan/vanidl/issues
Platform: UNKNOWN
Classifier: Programming Language :: Python :: 3
Classifier: License :: OSI Approved :: MIT License
Classifier: Operating System :: OS Independent
Requires-Python: >=3.6
License-File: LICENSE
Requires-Dist: numpy (==1.19.0)
Requires-Dist: pandas (==1.0.5)
